combi/MIT_license.txt
combi/__init__.py
combi/chain_space.py
combi/map_space.py
combi/misc.py
combi/product_space.py
combi/selection_space.py
combi/_python_toolbox/__init__.py
combi/_python_toolbox/comparison_tools.py
combi/_python_toolbox/cute_enum.py
combi/_python_toolbox/cute_iter_tools.py
combi/_python_toolbox/cute_testing.py
combi/_python_toolbox/decorator_tools.py
combi/_python_toolbox/dict_tools.py
combi/_python_toolbox/exceptions.py
combi/_python_toolbox/future_tools.py
combi/_python_toolbox/import_tools.py
combi/_python_toolbox/introspection_tools.py
combi/_python_toolbox/logic_tools.py
combi/_python_toolbox/monkeypatch_envelopes.py
combi/_python_toolbox/monkeypatching_tools.py
combi/_python_toolbox/package_finder.py
combi/_python_toolbox/sys_tools.py
combi/_python_toolbox/version_info.py
combi/_python_toolbox/_bootstrap/__init__.py
combi/_python_toolbox/_bootstrap/bootstrap.py
combi/_python_toolbox/binary_search/__init__.py
combi/_python_toolbox/binary_search/binary_search_profile.py
combi/_python_toolbox/binary_search/functions.py
combi/_python_toolbox/binary_search/roundings.py
combi/_python_toolbox/caching/__init__.py
combi/_python_toolbox/caching/cached_property.py
combi/_python_toolbox/caching/cached_type.py
combi/_python_toolbox/caching/decorators.py
combi/_python_toolbox/cheat_hashing/__init__.py
combi/_python_toolbox/cheat_hashing/cheat_hash.py
combi/_python_toolbox/cheat_hashing/cheat_hash_functions.py
combi/_python_toolbox/context_management/__init__.py
combi/_python_toolbox/context_management/abstract_context_manager.py
combi/_python_toolbox/context_management/blank_context_manager.py
combi/_python_toolbox/context_management/context_manager.py
combi/_python_toolbox/context_management/context_manager_type.py
combi/_python_toolbox/context_management/context_manager_type_type.py
combi/_python_toolbox/context_management/delegating_context_manager.py
combi/_python_toolbox/context_management/functions.py
combi-1.1.4.dist-info/LICENSE
combi-1.1.4.dist-info/METADATA
combi-1.1.4.dist-info/WHEEL
combi-1.1.4.dist-info/top_level.txt
combi-1.1.4.dist-info/RECORD
